typedschema/__init__.py
typedschema/_version.py
typedschema/codegen.py
typedschema/column.py
typedschema/schema.py
typedschema/string.py
typedschema/structfield.py
typedschema/table.py
pyspark_typedschema-0.0.6.dist-info/LICENSE
pyspark_typedschema-0.0.6.dist-info/METADATA
pyspark_typedschema-0.0.6.dist-info/WHEEL
pyspark_typedschema-0.0.6.dist-info/top_level.txt
pyspark_typedschema-0.0.6.dist-info/RECORD
