Metadata-Version: 2.1
Name: pyspark-typedschema
Version: 0.0.6
Summary: Define (typed) schemas for pyspark dataframes
Author-email: Joachim Bargsten <jw@bargsten.org>
License:                                  Apache License
Project-URL: homepage, https://github.com/jwbargsten/typedschema
Project-URL: repository, https://github.com/jwbargsten/typedschema
Keywords: pyspark
Requires-Python: >=3.10
License-File: LICENSE
Requires-Dist: pyspark
Provides-Extra: dev
Requires-Dist: ruff; extra == "dev"
Requires-Dist: pytest>=7; extra == "dev"
Requires-Dist: setuptools_scm; extra == "dev"
Requires-Dist: mypy; extra == "dev"
Requires-Dist: pytest-env; extra == "dev"
Requires-Dist: pytest-mock; extra == "dev"
Provides-Extra: build
Requires-Dist: build; extra == "build"
Requires-Dist: twine; extra == "build"
Requires-Dist: tomli; extra == "build"
Requires-Dist: setuptools_scm; extra == "build"
Requires-Dist: check-manifest; extra == "build"
Requires-Dist: check-wheel-contents; extra == "build"
Requires-Dist: pyroma; extra == "build"
Provides-Extra: docs
Requires-Dist: sphinx; extra == "docs"
Requires-Dist: myst-parser; extra == "docs"
Requires-Dist: sphinx-sitemap; extra == "docs"
Requires-Dist: setuptools_scm; extra == "docs"
Requires-Dist: pydata-sphinx-theme; extra == "docs"
Requires-Dist: sphinx-autodoc-typehints; extra == "docs"
Requires-Dist: myst-nb; extra == "docs"
Provides-Extra: all
Requires-Dist: pyspark-typedschema[build,dev,docs]; extra == "all"
